hermes/__init__.py
hermes/camera/CV2AsynchronousVideoCapture.py
hermes/camera/__init__.py
hermes/domain/AsynchronousIPChannel.py
hermes/domain/AsynchronousVideoCapture.py
hermes/domain/CheckedMessage.py
hermes/domain/Message.py
hermes/domain/MessageCodes.py
hermes/domain/__init__.py
hermes/messages/UDPMessage.py
hermes/messages/__init__.py
hermes/messages/tests/__init__.py
hermes/messages/tests/test_UDPMessage.py
hermes/network/AsyncUDPChannel.py
hermes/network/__init__.py
hermes/network/tests/__init__.py
hermes/network/tests/test_AsyncUDPChannel.py
hermes/security/Handshake.py
hermes/security/__init__.py
hermes/security/utils.py
hermes/security/tests/__init__.py
hermes/security/tests/test_Handshake.py
hermes/security/tests/test_utils.py
hermes/stream/ImageManager.py
hermes/stream/TopicManager.py
hermes/stream/VideoStream.py
hermes/stream/VideoTopic.py
hermes/stream/__init__.py
hermes/stream/tests/__init__.py
hermes/stream/tests/test_ImageManager.py
hermes/stream/tests/test_TopicManager.py
hermes/stream/tests/test_VideoStream.py
hermes/stream/tests/test_VideoTopic.py
hermes_alvarios-0.3.0.dist-info/LICENSE
hermes_alvarios-0.3.0.dist-info/METADATA
hermes_alvarios-0.3.0.dist-info/WHEEL
hermes_alvarios-0.3.0.dist-info/top_level.txt
hermes_alvarios-0.3.0.dist-info/RECORD
