Metadata-Version: 2.1
Name: hermes-alvarios
Version: 0.3.0
Summary: Network tools for python.
Home-page: https://github.com/Alvarios/Hermes
Author: CDulouard
Author-email: clement.dulouard@alvarios.com
License: GNU General Public License v3 (GPLv3)
Platform: UNKNOWN
Classifier: Programming Language :: Python :: 3
Classifier: License :: OSI Approved :: GNU General Public License v3 (GPLv3)
Classifier: Operating System :: OS Independent
Classifier: Development Status :: 3 - Alpha
Requires-Python: >=3.8
Requires-Dist: cffi
Requires-Dist: cryptography
Requires-Dist: numpy
Requires-Dist: opencv-python
